{
  "version": "7",
  "dialect": "postgresql",
  "entries": [
    {
      "idx": 0,
      "version": "7",
      "when": 1780746474187,
      "tag": "0000_conscious_aqueduct",
      "breakpoints": true
    },
    {
      "idx": 1,
      "version": "7",
      "when": 1780761250139,
      "tag": "0001_tranquil_giant_man",
      "breakpoints": true
    },
    {
      "idx": 2,
      "version": "7",
      "when": 1780831399753,
      "tag": "0002_needy_ares",
      "breakpoints": true
    },
    {
      "idx": 3,
      "version": "7",
      "when": 1781633637995,
      "tag": "0003_tense_wendigo",
      "breakpoints": true
    },
    {
      "idx": 4,
      "version": "7",
      "when": 1781797538139,
      "tag": "0004_skinny_rictor",
      "breakpoints": true
    },
    {
      "idx": 5,
      "version": "7",
      "when": 1781900737238,
      "tag": "0005_silly_spacker_dave",
      "breakpoints": true
    }
  ]
}